{"type":"FeatureCollection","features":[{"type":"Feature","geometry":{"type":"Point","coordinates":[-73.990892,40.735053]},"properties":{"title":"\"Direct Action Flaneur\" - End Police Brutality March","marker-color":"#ad6638","marker-size":"small","marker-symbol":"hospital","image":"http:\/\/\/farm8.staticflickr.com\/7178\/7012557295_4b29d34abe_q.jpg","url":"http:\/\/\/farm8.staticflickr.com\/7178\/7012557295_4b29d34abe.jpg"}},{"type":"Feature","geometry":{"type":"Point","coordinates":[-73.98778,40.724799]},"properties":{"title":"clark-nova.","marker-color":"#ad6638","marker-size":"small","marker-symbol":"hospital","image":"http:\/\/\/farm6.staticflickr.com\/5100\/5418934017_011f048daf_q.jpg","url":"http:\/\/\/farm6.staticflickr.com\/5100\/5418934017_011f048daf.jpg"}},{"type":"Feature","geometry":{"type":"Point","coordinates":[-73.983296,40.739159]},"properties":{"title":"frustration","marker-color":"#ad6638","marker-size":"small","marker-symbol":"hospital","image":"http:\/\/\/farm5.staticflickr.com\/4052\/4668399472_254886e613_q.jpg","url":"http:\/\/\/farm5.staticflickr.com\/4052\/4668399472_254886e613.jpg"}},{"type":"Feature","geometry":{"type":"Point","coordinates":[-74.007178,40.716179]},"properties":{"title":"Get the Wite-Out","marker-color":"#ad6638","marker-size":"small","marker-symbol":"hospital","image":"http:\/\/\/farm4.staticflickr.com\/3651\/3643148658_68e9ed5006_q.jpg","url":"http:\/\/\/farm4.staticflickr.com\/3651\/3643148658_68e9ed5006.jpg"}},{"type":"Feature","geometry":{"type":"Point","coordinates":[-73.982276,40.753271]},"properties":{"title":"e. e. cummings's typewriter (shift key looks fine to me)","marker-color":"#ad6638","marker-size":"small","marker-symbol":"hospital","image":"http:\/\/\/farm8.staticflickr.com\/7034\/6736775123_c347f3b747_q.jpg","url":"http:\/\/\/farm8.staticflickr.com\/7034\/6736775123_c347f3b747.jpg"}},{"type":"Feature","geometry":{"type":"Point","coordinates":[-73.982319,40.753324]},"properties":{"title":"NYC - Midtown - New York Public Library Main Building - On the Road Scroll Manuscript","marker-color":"#ad6638","marker-size":"small","marker-symbol":"hospital","image":"http:\/\/\/farm3.staticflickr.com\/2114\/2065529665_54f18326a3_q.jpg","url":"http:\/\/\/farm3.staticflickr.com\/2114\/2065529665_54f18326a3.jpg"}},{"type":"Feature","geometry":{"type":"Point","coordinates":[-74.009839,40.750918]},"properties":{"title":"Varityper","marker-color":"#ad6638","marker-size":"small","marker-symbol":"hospital","image":"http:\/\/\/farm1.staticflickr.com\/77\/191314554_3103df2c1a_q.jpg","url":"http:\/\/\/farm1.staticflickr.com\/77\/191314554_3103df2c1a.jpg"}},{"type":"Feature","geometry":{"type":"Point","coordinates":[-74.011158,40.709224]},"properties":{"title":"\"DIRECT ACTION FLANEURS\" - End Police Brutality March","marker-color":"#ad6638","marker-size":"small","marker-symbol":"hospital","image":"http:\/\/\/farm8.staticflickr.com\/7251\/6866327650_c8a41b1079_q.jpg","url":"http:\/\/\/farm8.staticflickr.com\/7251\/6866327650_c8a41b1079.jpg"}},{"type":"Feature","geometry":{"type":"Point","coordinates":[-74.011158,40.709224]},"properties":{"title":"\"DIRECT ACTION FLANEURS\" - End Police Brutality March","marker-color":"#ad6638","marker-size":"small","marker-symbol":"hospital","image":"http:\/\/\/farm7.staticflickr.com\/6045\/7012440745_b7a89e0144_q.jpg","url":"http:\/\/\/farm7.staticflickr.com\/6045\/7012440745_b7a89e0144.jpg"}},{"type":"Feature","geometry":{"type":"Point","coordinates":[-74.008758,40.752294]},"properties":{"title":"Lightship #115 \"Frying Pan\": Typewriter","marker-color":"#ad6638","marker-size":"small","marker-symbol":"hospital","image":"http:\/\/\/farm3.staticflickr.com\/2728\/4459465068_fb1accafac_q.jpg","url":"http:\/\/\/farm3.staticflickr.com\/2728\/4459465068_fb1accafac.jpg"}},{"type":"Feature","geometry":{"type":"Point","coordinates":[-73.996438,40.769638]},"properties":{"title":"Installation by Peter Liversidge: Come On In \/ The Armory Show 2010 \/ 20100305.7D.03950 \/ SML","marker-color":"#ad6638","marker-size":"small","marker-symbol":"hospital","image":"http:\/\/\/farm5.staticflickr.com\/4058\/4420147003_5e5dec7ed6_q.jpg","url":"http:\/\/\/farm5.staticflickr.com\/4058\/4420147003_5e5dec7ed6.jpg"}},{"type":"Feature","geometry":{"type":"Point","coordinates":[-73.953759,40.714248]},"properties":{"title":"coffees and letters {monsters of new york} #monster #monstersofny #illustration #newyork #character #cartoon #coffee #cafe #typewriter","marker-color":"#ad6638","marker-size":"small","marker-symbol":"hospital","image":"http:\/\/\/farm8.staticflickr.com\/7300\/9307894377_22d8a2697d_q.jpg","url":"http:\/\/\/farm8.staticflickr.com\/7300\/9307894377_22d8a2697d.jpg"}},{"type":"Feature","geometry":{"type":"Point","coordinates":[-73.943585,40.71273]},"properties":{"title":"Rustic aesthetic #typewriters #brooklyn","marker-color":"#ad6638","marker-size":"small","marker-symbol":"hospital","image":"http:\/\/\/farm3.staticflickr.com\/2808\/9334089798_9f6607a7d5_q.jpg","url":"http:\/\/\/farm3.staticflickr.com\/2808\/9334089798_9f6607a7d5.jpg"}},{"type":"Feature","geometry":{"type":"Point","coordinates":[-73.960585,40.778477]},"properties":{"title":"In the Midst of Winter","marker-color":"#ad6638","marker-size":"small","marker-symbol":"hospital","image":"http:\/\/\/farm9.staticflickr.com\/8223\/8293683013_e6f5fe1886_q.jpg","url":"http:\/\/\/farm9.staticflickr.com\/8223\/8293683013_e6f5fe1886.jpg"}},{"type":"Feature","geometry":{"type":"Point","coordinates":[-73.948402,40.672405]},"properties":{"title":"Brooklyn, NYC","marker-color":"#ad6638","marker-size":"small","marker-symbol":"hospital","image":"http:\/\/\/farm1.staticflickr.com\/1\/4465174_1651d91d38_q.jpg","url":"http:\/\/\/farm1.staticflickr.com\/1\/4465174_1651d91d38.jpg"}},{"type":"Feature","geometry":{"type":"Point","coordinates":[-74.103604,40.827459]},"properties":{"title":"Untitled","marker-color":"#ad6638","marker-size":"small","marker-symbol":"hospital","image":"http:\/\/\/farm9.staticflickr.com\/8042\/7923573298_c5553d2f26_q.jpg","url":"http:\/\/\/farm9.staticflickr.com\/8042\/7923573298_c5553d2f26.jpg"}},{"type":"Feature","geometry":{"type":"Point","coordinates":[-73.991909,40.729321]},"properties":{"title":"Typewriter","marker-color":"#ad6638","marker-size":"small","marker-symbol":"hospital","image":"http:\/\/\/farm3.staticflickr.com\/2784\/4398531114_4cecf55129_q.jpg","url":"http:\/\/\/farm3.staticflickr.com\/2784\/4398531114_4cecf55129.jpg"}},{"type":"Feature","geometry":{"type":"Point","coordinates":[-73.997245,40.730869]},"properties":{"title":"cross legged girl at the typewriter","marker-color":"#ad6638","marker-size":"small","marker-symbol":"hospital","image":"http:\/\/\/farm9.staticflickr.com\/8240\/8564010514_a36dbc5c3f_q.jpg","url":"http:\/\/\/farm9.staticflickr.com\/8240\/8564010514_a36dbc5c3f.jpg"}},{"type":"Feature","geometry":{"type":"Point","coordinates":[-73.993111,40.734962]},"properties":{"title":"1499 Sterling","marker-color":"#ad6638","marker-size":"small","marker-symbol":"hospital","image":"http:\/\/\/farm9.staticflickr.com\/8331\/8120952288_39261e0a8f_q.jpg","url":"http:\/\/\/farm9.staticflickr.com\/8331\/8120952288_39261e0a8f.jpg"}},{"type":"Feature","geometry":{"type":"Point","coordinates":[-73.995763,40.735002]},"properties":{"title":"Typecon'05 New York_242","marker-color":"#ad6638","marker-size":"small","marker-symbol":"hospital","image":"http:\/\/\/farm3.staticflickr.com\/2191\/2354028746_3f72353460_q.jpg","url":"http:\/\/\/farm3.staticflickr.com\/2191\/2354028746_3f72353460.jpg"}},{"type":"Feature","geometry":{"type":"Point","coordinates":[-73.995948,40.723487]},"properties":{"title":"Typewriter Wisdom","marker-color":"#ad6638","marker-size":"small","marker-symbol":"hospital","image":"http:\/\/\/farm5.staticflickr.com\/4147\/5094972279_8efb577e68_q.jpg","url":"http:\/\/\/farm5.staticflickr.com\/4147\/5094972279_8efb577e68.jpg"}},{"type":"Feature","geometry":{"type":"Point","coordinates":[-73.99293,40.722148]},"properties":{"title":"Hermes Rocket","marker-color":"#ad6638","marker-size":"small","marker-symbol":"hospital","image":"http:\/\/\/farm5.staticflickr.com\/4154\/5177295087_8e3ec8c8cc_q.jpg","url":"http:\/\/\/farm5.staticflickr.com\/4154\/5177295087_8e3ec8c8cc.jpg"}},{"type":"Feature","geometry":{"type":"Point","coordinates":[-73.985836,40.728743]},"properties":{"title":"Typewriter!","marker-color":"#ad6638","marker-size":"small","marker-symbol":"hospital","image":"http:\/\/\/farm7.staticflickr.com\/6059\/6319389363_5c0037c129_q.jpg","url":"http:\/\/\/farm7.staticflickr.com\/6059\/6319389363_5c0037c129.jpg"}},{"type":"Feature","geometry":{"type":"Point","coordinates":[-73.984697,40.728231]},"properties":{"title":"Type","marker-color":"#ad6638","marker-size":"small","marker-symbol":"hospital","image":"http:\/\/\/farm4.staticflickr.com\/3517\/5713189138_5065869258_q.jpg","url":"http:\/\/\/farm4.staticflickr.com\/3517\/5713189138_5065869258.jpg"}},{"type":"Feature","geometry":{"type":"Point","coordinates":[-73.994328,40.720452]},"properties":{"title":"the underground writing room at PUBLISH! #nyc #book #bea13 #underground #typewriter #writlarge #publishing","marker-color":"#ad6638","marker-size":"small","marker-symbol":"hospital","image":"http:\/\/\/farm8.staticflickr.com\/7372\/8902859926_f6d3fdced0_q.jpg","url":"http:\/\/\/farm8.staticflickr.com\/7372\/8902859926_f6d3fdced0.jpg"}},{"type":"Feature","geometry":{"type":"Point","coordinates":[-74.000334,40.721166]},"properties":{"title":"Vintage typewriters","marker-color":"#ad6638","marker-size":"small","marker-symbol":"hospital","image":"http:\/\/\/farm7.staticflickr.com\/6043\/6357362501_6b6d492409_q.jpg","url":"http:\/\/\/farm7.staticflickr.com\/6043\/6357362501_6b6d492409.jpg"}},{"type":"Feature","geometry":{"type":"Point","coordinates":[-74.008681,40.721825]},"properties":{"title":"Some light reading and a coffee. Maybe I'll use the typewriter to ink a novel or two.","marker-color":"#ad6638","marker-size":"small","marker-symbol":"hospital","image":"http:\/\/\/farm6.staticflickr.com\/5145\/5589080642_66fba5a5bb_q.jpg","url":"http:\/\/\/farm6.staticflickr.com\/5145\/5589080642_66fba5a5bb.jpg"}},{"type":"Feature","geometry":{"type":"Point","coordinates":[-73.977667,40.724167]},"properties":{"title":"The Underwood manual typewriter from dad's basement, meant to revolutionize my writing, serves mainly as iPad stand.","marker-color":"#ad6638","marker-size":"small","marker-symbol":"hospital","image":"http:\/\/\/farm7.staticflickr.com\/6072\/6118843638_219ab6d90c_q.jpg","url":"http:\/\/\/farm7.staticflickr.com\/6072\/6118843638_219ab6d90c.jpg"}},{"type":"Feature","geometry":{"type":"Point","coordinates":[-74.005451,40.742241]},"properties":{"title":"Shift #freedom #typewriter #key","marker-color":"#ad6638","marker-size":"small","marker-symbol":"hospital","image":"http:\/\/\/farm6.staticflickr.com\/5511\/9271432999_fc45d84635_q.jpg","url":"http:\/\/\/farm6.staticflickr.com\/5511\/9271432999_fc45d84635.jpg"}},{"type":"Feature","geometry":{"type":"Point","coordinates":[-74.004707,40.716079]},"properties":{"title":"Monarch Pioneer","marker-color":"#ad6638","marker-size":"small","marker-symbol":"hospital","image":"http:\/\/\/farm6.staticflickr.com\/5005\/5271420095_8f7353befe_q.jpg","url":"http:\/\/\/farm6.staticflickr.com\/5005\/5271420095_8f7353befe.jpg"}},{"type":"Feature","geometry":{"type":"Point","coordinates":[-74.004707,40.716079]},"properties":{"title":"Farbbanddose REMTICO","marker-color":"#ad6638","marker-size":"small","marker-symbol":"hospital","image":"http:\/\/\/farm6.staticflickr.com\/5283\/5229589327_f135b74161_q.jpg","url":"http:\/\/\/farm6.staticflickr.com\/5283\/5229589327_f135b74161.jpg"}},{"type":"Feature","geometry":{"type":"Point","coordinates":[-74.004707,40.716079]},"properties":{"title":"Monarch Pioneer","marker-color":"#ad6638","marker-size":"small","marker-symbol":"hospital","image":"http:\/\/\/farm6.staticflickr.com\/5090\/5272028028_48e8b52ac5_q.jpg","url":"http:\/\/\/farm6.staticflickr.com\/5090\/5272028028_48e8b52ac5.jpg"}},{"type":"Feature","geometry":{"type":"Point","coordinates":[-74.004707,40.716079]},"properties":{"title":"Monarch Pioneer","marker-color":"#ad6638","marker-size":"small","marker-symbol":"hospital","image":"http:\/\/\/farm6.staticflickr.com\/5163\/5271379611_51c838cd6a_q.jpg","url":"http:\/\/\/farm6.staticflickr.com\/5163\/5271379611_51c838cd6a.jpg"}},{"type":"Feature","geometry":{"type":"Point","coordinates":[-73.991128,40.749922]},"properties":{"title":"The Next HOPE - USB typewriter.","marker-color":"#ad6638","marker-size":"small","marker-symbol":"hospital","image":"http:\/\/\/farm5.staticflickr.com\/4143\/4803495198_bab781743a_q.jpg","url":"http:\/\/\/farm5.staticflickr.com\/4143\/4803495198_bab781743a.jpg"}},{"type":"Feature","geometry":{"type":"Point","coordinates":[-74.005869,40.746387]},"properties":{"title":"Missing room_Booklet_P30-31","marker-color":"#ad6638","marker-size":"small","marker-symbol":"hospital","image":"http:\/\/\/farm7.staticflickr.com\/6174\/6185277890_c0cab59afe_q.jpg","url":"http:\/\/\/farm7.staticflickr.com\/6174\/6185277890_c0cab59afe.jpg"}},{"type":"Feature","geometry":{"type":"Point","coordinates":[-74.010556,40.714166]},"properties":{"title":"124\/365","marker-color":"#ad6638","marker-size":"small","marker-symbol":"hospital","image":"http:\/\/\/farm6.staticflickr.com\/5020\/5538421467_5a321392c1_q.jpg","url":"http:\/\/\/farm6.staticflickr.com\/5020\/5538421467_5a321392c1.jpg"}},{"type":"Feature","geometry":{"type":"Point","coordinates":[-74.00595,40.709297]},"properties":{"title":"Copier, Facsimile, Typewriter","marker-color":"#ad6638","marker-size":"small","marker-symbol":"hospital","image":"http:\/\/\/farm3.staticflickr.com\/2788\/4248692682_3cd1f1e974_q.jpg","url":"http:\/\/\/farm3.staticflickr.com\/2788\/4248692682_3cd1f1e974.jpg"}},{"type":"Feature","geometry":{"type":"Point","coordinates":[-74.00985,40.712207]},"properties":{"title":"Underwood Building, Lower Manhattan","marker-color":"#ad6638","marker-size":"small","marker-symbol":"hospital","image":"http:\/\/\/farm3.staticflickr.com\/2855\/9256993107_51bf1951fb_q.jpg","url":"http:\/\/\/farm3.staticflickr.com\/2855\/9256993107_51bf1951fb.jpg"}},{"type":"Feature","geometry":{"type":"Point","coordinates":[-73.982582,40.753291]},"properties":{"title":"E. E. Cummings' Typewriter","marker-color":"#ad6638","marker-size":"small","marker-symbol":"hospital","image":"http:\/\/\/farm4.staticflickr.com\/3169\/5756017167_75f7722aff_q.jpg","url":"http:\/\/\/farm4.staticflickr.com\/3169\/5756017167_75f7722aff.jpg"}},{"type":"Feature","geometry":{"type":"Point","coordinates":[-73.989036,40.755645]},"properties":{"title":"Typewriter 04","marker-color":"#ad6638","marker-size":"small","marker-symbol":"hospital","image":"http:\/\/\/farm9.staticflickr.com\/8382\/8578233068_89b0444e88_q.jpg","url":"http:\/\/\/farm9.staticflickr.com\/8382\/8578233068_89b0444e88.jpg"}},{"type":"Feature","geometry":{"type":"Point","coordinates":[-73.989036,40.755645]},"properties":{"title":"Typewriter 01","marker-color":"#ad6638","marker-size":"small","marker-symbol":"hospital","image":"http:\/\/\/farm9.staticflickr.com\/8506\/8574687003_3ac7a5330c_q.jpg","url":"http:\/\/\/farm9.staticflickr.com\/8506\/8574687003_3ac7a5330c.jpg"}},{"type":"Feature","geometry":{"type":"Point","coordinates":[-73.989036,40.755645]},"properties":{"title":"Typewriter 05","marker-color":"#ad6638","marker-size":"small","marker-symbol":"hospital","image":"http:\/\/\/farm9.staticflickr.com\/8375\/8577138041_b0d057165e_q.jpg","url":"http:\/\/\/farm9.staticflickr.com\/8375\/8577138041_b0d057165e.jpg"}},{"type":"Feature","geometry":{"type":"Point","coordinates":[-73.989036,40.755645]},"properties":{"title":"Typewriter 02","marker-color":"#ad6638","marker-size":"small","marker-symbol":"hospital","image":"http:\/\/\/farm9.staticflickr.com\/8091\/8575793606_5db8bf7ef4_q.jpg","url":"http:\/\/\/farm9.staticflickr.com\/8091\/8575793606_5db8bf7ef4.jpg"}},{"type":"Feature","geometry":{"type":"Point","coordinates":[-73.989036,40.755645]},"properties":{"title":"Typewriter 06","marker-color":"#ad6638","marker-size":"small","marker-symbol":"hospital","image":"http:\/\/\/farm9.staticflickr.com\/8107\/8577155979_18365e5c04_q.jpg","url":"http:\/\/\/farm9.staticflickr.com\/8107\/8577155979_18365e5c04.jpg"}},{"type":"Feature","geometry":{"type":"Point","coordinates":[-74.008895,40.751897]},"properties":{"title":"long long ago, there was a ... typewriter","marker-color":"#ad6638","marker-size":"small","marker-symbol":"hospital","image":"http:\/\/\/farm4.staticflickr.com\/3044\/2819240767_1bd240dc33_q.jpg","url":"http:\/\/\/farm4.staticflickr.com\/3044\/2819240767_1bd240dc33.jpg"}},{"type":"Feature","geometry":{"type":"Point","coordinates":[-73.963319,40.720591]},"properties":{"title":"Royal Typewriter","marker-color":"#ad6638","marker-size":"small","marker-symbol":"hospital","image":"http:\/\/\/farm9.staticflickr.com\/8024\/7450904842_87375e8f21_q.jpg","url":"http:\/\/\/farm9.staticflickr.com\/8024\/7450904842_87375e8f21.jpg"}},{"type":"Feature","geometry":{"type":"Point","coordinates":[-74.011528,40.703086]},"properties":{"title":"Repair tools II - 13","marker-color":"#ad6638","marker-size":"small","marker-symbol":"hospital","image":"http:\/\/\/farm6.staticflickr.com\/5020\/5491993315_69aff195d1_q.jpg","url":"http:\/\/\/farm6.staticflickr.com\/5020\/5491993315_69aff195d1.jpg"}},{"type":"Feature","geometry":{"type":"Point","coordinates":[-74.011528,40.703086]},"properties":{"title":"Repair tools II - 12","marker-color":"#ad6638","marker-size":"small","marker-symbol":"hospital","image":"http:\/\/\/farm6.staticflickr.com\/5020\/5492587136_a2ccca1fb6_q.jpg","url":"http:\/\/\/farm6.staticflickr.com\/5020\/5492587136_a2ccca1fb6.jpg"}},{"type":"Feature","geometry":{"type":"Point","coordinates":[-73.96264,40.720518]},"properties":{"title":"Keys","marker-color":"#ad6638","marker-size":"small","marker-symbol":"hospital","image":"http:\/\/\/farm9.staticflickr.com\/8293\/7638881414_ab716ddf57_q.jpg","url":"http:\/\/\/farm9.staticflickr.com\/8293\/7638881414_ab716ddf57.jpg"}},{"type":"Feature","geometry":{"type":"Point","coordinates":[-73.962384,40.719503]},"properties":{"title":"Typewriters","marker-color":"#ad6638","marker-size":"small","marker-symbol":"hospital","image":"http:\/\/\/farm8.staticflickr.com\/7153\/6533827587_258f52a89a_q.jpg","url":"http:\/\/\/farm8.staticflickr.com\/7153\/6533827587_258f52a89a.jpg"}},{"type":"Feature","geometry":{"type":"Point","coordinates":[-73.979191,40.762163]},"properties":{"title":"typewriter","marker-color":"#ad6638","marker-size":"small","marker-symbol":"hospital","image":"http:\/\/\/farm4.staticflickr.com\/3233\/2977511055_5f4430040e_q.jpg","url":"http:\/\/\/farm4.staticflickr.com\/3233\/2977511055_5f4430040e.jpg"}},{"type":"Feature","geometry":{"type":"Point","coordinates":[-73.977593,40.76143]},"properties":{"title":"Rheinmetall \/ Victoria 8","marker-color":"#ad6638","marker-size":"small","marker-symbol":"hospital","image":"http:\/\/\/farm4.staticflickr.com\/3291\/2518673456_1ab79cd344_q.jpg","url":"http:\/\/\/farm4.staticflickr.com\/3291\/2518673456_1ab79cd344.jpg"}},{"type":"Feature","geometry":{"type":"Point","coordinates":[-73.977593,40.76143]},"properties":{"title":"Rheinmetall \/ Victoria 8","marker-color":"#ad6638","marker-size":"small","marker-symbol":"hospital","image":"http:\/\/\/farm3.staticflickr.com\/2373\/2518670736_d18bcdfc4a_q.jpg","url":"http:\/\/\/farm3.staticflickr.com\/2373\/2518670736_d18bcdfc4a.jpg"}},{"type":"Feature","geometry":{"type":"Point","coordinates":[-73.977593,40.76143]},"properties":{"title":"Rheinmetall \/ Victoria 8","marker-color":"#ad6638","marker-size":"small","marker-symbol":"hospital","image":"http:\/\/\/farm3.staticflickr.com\/2326\/2517874061_d000983f52_q.jpg","url":"http:\/\/\/farm3.staticflickr.com\/2326\/2517874061_d000983f52.jpg"}},{"type":"Feature","geometry":{"type":"Point","coordinates":[-73.977041,40.761164]},"properties":{"title":"Rheinmetall\/VIctoria B - Rodney Graham video","marker-color":"#ad6638","marker-size":"small","marker-symbol":"hospital","image":"http:\/\/\/farm4.staticflickr.com\/3049\/2669754189_bdd40de955_q.jpg","url":"http:\/\/\/farm4.staticflickr.com\/3049\/2669754189_bdd40de955.jpg"}},{"type":"Feature","geometry":{"type":"Point","coordinates":[-73.977481,40.761686]},"properties":{"title":"Project.","marker-color":"#ad6638","marker-size":"small","marker-symbol":"hospital","image":"http:\/\/\/farm3.staticflickr.com\/2125\/2260546028_28b701b679_q.jpg","url":"http:\/\/\/farm3.staticflickr.com\/2125\/2260546028_28b701b679.jpg"}},{"type":"Feature","geometry":{"type":"Point","coordinates":[-73.977384,40.761658]},"properties":{"title":"MoMA - Rheinmetall\/Victoria","marker-color":"#ad6638","marker-size":"small","marker-symbol":"hospital","image":"http:\/\/\/farm4.staticflickr.com\/3269\/2300509348_11b7fceda7_q.jpg","url":"http:\/\/\/farm4.staticflickr.com\/3269\/2300509348_11b7fceda7.jpg"}},{"type":"Feature","geometry":{"type":"Point","coordinates":[-73.958474,40.718459]},"properties":{"title":"399-730 Keylinks","marker-color":"#ad6638","marker-size":"small","marker-symbol":"hospital","image":"http:\/\/\/farm3.staticflickr.com\/2664\/4022693464_5c1d049ff6_q.jpg","url":"http:\/\/\/farm3.staticflickr.com\/2664\/4022693464_5c1d049ff6.jpg"}},{"type":"Feature","geometry":{"type":"Point","coordinates":[-74.030095,40.716741]},"properties":{"title":"one big fish","marker-color":"#ad6638","marker-size":"small","marker-symbol":"hospital","image":"http:\/\/\/farm5.staticflickr.com\/4108\/5195911544_ea5ccf2c61_q.jpg","url":"http:\/\/\/farm5.staticflickr.com\/4108\/5195911544_ea5ccf2c61.jpg"}},{"type":"Feature","geometry":{"type":"Point","coordinates":[-73.994862,40.690388]},"properties":{"title":"Cameras, Typewriters & Hand-sliced Prosciutto at the Brooklyn Flea","marker-color":"#ad6638","marker-size":"small","marker-symbol":"hospital","image":"http:\/\/\/farm6.staticflickr.com\/5182\/5690990540_fe5b6e060c_q.jpg","url":"http:\/\/\/farm6.staticflickr.com\/5182\/5690990540_fe5b6e060c.jpg"}},{"type":"Feature","geometry":{"type":"Point","coordinates":[-73.957203,40.714559]},"properties":{"title":"typewriter.JPG","marker-color":"#ad6638","marker-size":"small","marker-symbol":"hospital","image":"http:\/\/\/farm4.staticflickr.com\/3355\/3485385821_8986355188_q.jpg","url":"http:\/\/\/farm4.staticflickr.com\/3355\/3485385821_8986355188.jpg"}},{"type":"Feature","geometry":{"type":"Point","coordinates":[-73.995924,40.769353]},"properties":{"title":"Hebrew Arabic typewriter","marker-color":"#ad6638","marker-size":"small","marker-symbol":"hospital","image":"http:\/\/\/farm8.staticflickr.com\/7040\/6823245578_de2a03738f_q.jpg","url":"http:\/\/\/farm8.staticflickr.com\/7040\/6823245578_de2a03738f.jpg"}},{"type":"Feature","geometry":{"type":"Point","coordinates":[-73.98306,40.691523]},"properties":{"title":"Cufflinks.","marker-color":"#ad6638","marker-size":"small","marker-symbol":"hospital","image":"http:\/\/\/farm7.staticflickr.com\/6154\/6170688881_229f57d5ba_q.jpg","url":"http:\/\/\/farm7.staticflickr.com\/6154\/6170688881_229f57d5ba.jpg"}},{"type":"Feature","geometry":{"type":"Point","coordinates":[-73.951721,40.720979]},"properties":{"title":"Renegade Craft Fair","marker-color":"#ad6638","marker-size":"small","marker-symbol":"hospital","image":"http:\/\/\/farm7.staticflickr.com\/6128\/5962983338_a7c10c7e17_q.jpg","url":"http:\/\/\/farm7.staticflickr.com\/6128\/5962983338_a7c10c7e17.jpg"}},{"type":"Feature","geometry":{"type":"Point","coordinates":[-74.037905,40.712374]},"properties":{"title":"swimming with the fishes","marker-color":"#ad6638","marker-size":"small","marker-symbol":"hospital","image":"http:\/\/\/farm5.staticflickr.com\/4088\/5193292672_a865f798f6_q.jpg","url":"http:\/\/\/farm5.staticflickr.com\/4088\/5193292672_a865f798f6.jpg"}},{"type":"Feature","geometry":{"type":"Point","coordinates":[-73.986927,40.682696]},"properties":{"title":"Typewriter","marker-color":"#ad6638","marker-size":"small","marker-symbol":"hospital","image":"http:\/\/\/farm3.staticflickr.com\/2019\/2234171348_286d50bcc5_q.jpg","url":"http:\/\/\/farm3.staticflickr.com\/2019\/2234171348_286d50bcc5.jpg"}},{"type":"Feature","geometry":{"type":"Point","coordinates":[-73.986927,40.682696]},"properties":{"title":"Typewriter","marker-color":"#ad6638","marker-size":"small","marker-symbol":"hospital","image":"http:\/\/\/farm3.staticflickr.com\/2108\/2233386105_265518d932_q.jpg","url":"http:\/\/\/farm3.staticflickr.com\/2108\/2233386105_265518d932.jpg"}},{"type":"Feature","geometry":{"type":"Point","coordinates":[-73.986927,40.682696]},"properties":{"title":"Typewriter","marker-color":"#ad6638","marker-size":"small","marker-symbol":"hospital","image":"http:\/\/\/farm3.staticflickr.com\/2132\/2233380207_96f8210e27_q.jpg","url":"http:\/\/\/farm3.staticflickr.com\/2132\/2233380207_96f8210e27.jpg"}},{"type":"Feature","geometry":{"type":"Point","coordinates":[-73.981561,40.683715]},"properties":{"title":"Typewriter repair","marker-color":"#ad6638","marker-size":"small","marker-symbol":"hospital","image":"http:\/\/\/farm8.staticflickr.com\/7041\/6794821842_4634a6114e_q.jpg","url":"http:\/\/\/farm8.staticflickr.com\/7041\/6794821842_4634a6114e.jpg"}},{"type":"Feature","geometry":{"type":"Point","coordinates":[-73.981589,40.683687]},"properties":{"title":"This won't hurt a bit","marker-color":"#ad6638","marker-size":"small","marker-symbol":"hospital","image":"http:\/\/\/farm8.staticflickr.com\/7068\/6794823514_6074550f4b_q.jpg","url":"http:\/\/\/farm8.staticflickr.com\/7068\/6794823514_6074550f4b.jpg"}},{"type":"Feature","geometry":{"type":"Point","coordinates":[-73.969334,40.6875]},"properties":{"title":"Underwood Golden Touch typewriter","marker-color":"#ad6638","marker-size":"small","marker-symbol":"hospital","image":"http:\/\/\/farm5.staticflickr.com\/4003\/5165827926_a4f1bd75a4_q.jpg","url":"http:\/\/\/farm5.staticflickr.com\/4003\/5165827926_a4f1bd75a4.jpg"}},{"type":"Feature","geometry":{"type":"Point","coordinates":[-73.969252,40.687504]},"properties":{"title":"Underwood Portable typewriter","marker-color":"#ad6638","marker-size":"small","marker-symbol":"hospital","image":"http:\/\/\/farm2.staticflickr.com\/1257\/5165827716_329ed3cb8f_q.jpg","url":"http:\/\/\/farm2.staticflickr.com\/1257\/5165827716_329ed3cb8f.jpg"}},{"type":"Feature","geometry":{"type":"Point","coordinates":[-73.969187,40.687504]},"properties":{"title":"Smith & Corona Standard typewriter","marker-color":"#ad6638","marker-size":"small","marker-symbol":"hospital","image":"http:\/\/\/farm5.staticflickr.com\/4084\/5165828122_71886e1140_q.jpg","url":"http:\/\/\/farm5.staticflickr.com\/4084\/5165828122_71886e1140.jpg"}},{"type":"Feature","geometry":{"type":"Point","coordinates":[-73.969225,40.687415]},"properties":{"title":"Typewriter cuff links at the Brooklyn Flea #latergram #brooklyn #type #typewriter #brooklynflea #fleamarkets","marker-color":"#ad6638","marker-size":"small","marker-symbol":"hospital","image":"http:\/\/\/farm9.staticflickr.com\/8081\/8297207728_21874545ca_q.jpg","url":"http:\/\/\/farm9.staticflickr.com\/8081\/8297207728_21874545ca.jpg"}},{"type":"Feature","geometry":{"type":"Point","coordinates":[-73.969166,40.687431]},"properties":{"title":"Flea Market Sales","marker-color":"#ad6638","marker-size":"small","marker-symbol":"hospital","image":"http:\/\/\/farm6.staticflickr.com\/5144\/5597116402_60e9753cdd_q.jpg","url":"http:\/\/\/farm6.staticflickr.com\/5144\/5597116402_60e9753cdd.jpg"}},{"type":"Feature","geometry":{"type":"Point","coordinates":[-73.969167,40.687333]},"properties":{"title":"","marker-color":"#ad6638","marker-size":"small","marker-symbol":"hospital","image":"http:\/\/\/farm9.staticflickr.com\/8151\/6977108254_e25a7f2e35_q.jpg","url":"http:\/\/\/farm9.staticflickr.com\/8151\/6977108254_e25a7f2e35.jpg"}},{"type":"Feature","geometry":{"type":"Point","coordinates":[-73.995971,40.678192]},"properties":{"title":"Hm...lets see here how to get the sound to come out of that typewriter","marker-color":"#ad6638","marker-size":"small","marker-symbol":"hospital","image":"http:\/\/\/farm9.staticflickr.com\/8145\/7121031765_2155ba4af8_q.jpg","url":"http:\/\/\/farm9.staticflickr.com\/8145\/7121031765_2155ba4af8.jpg"}},{"type":"Feature","geometry":{"type":"Point","coordinates":[-73.94126,40.726181]},"properties":{"title":"The Olivetti Lettera 22","marker-color":"#ad6638","marker-size":"small","marker-symbol":"hospital","image":"http:\/\/\/farm6.staticflickr.com\/5045\/5355994478_3d53f2bf79_q.jpg","url":"http:\/\/\/farm6.staticflickr.com\/5045\/5355994478_3d53f2bf79.jpg"}},{"type":"Feature","geometry":{"type":"Point","coordinates":[-73.986334,40.677166]},"properties":{"title":"Plainsawn sign at Twig","marker-color":"#ad6638","marker-size":"small","marker-symbol":"hospital","image":"http:\/\/\/farm9.staticflickr.com\/8423\/7688818860_fe6296b979_q.jpg","url":"http:\/\/\/farm9.staticflickr.com\/8423\/7688818860_fe6296b979.jpg"}},{"type":"Feature","geometry":{"type":"Point","coordinates":[-74.039976,40.699552]},"properties":{"title":"Missing room_Booklet_P18-19","marker-color":"#ad6638","marker-size":"small","marker-symbol":"hospital","image":"http:\/\/\/farm7.staticflickr.com\/6176\/6184933615_8a62fca844_q.jpg","url":"http:\/\/\/farm7.staticflickr.com\/6176\/6184933615_8a62fca844.jpg"}},{"type":"Feature","geometry":{"type":"Point","coordinates":[-73.940032,40.715917]},"properties":{"title":"Found a tiny Alice on a typewriter.","marker-color":"#ad6638","marker-size":"small","marker-symbol":"hospital","image":"http:\/\/\/farm9.staticflickr.com\/8326\/8105151779_6bcb8ee1c1_q.jpg","url":"http:\/\/\/farm9.staticflickr.com\/8326\/8105151779_6bcb8ee1c1.jpg"}},{"type":"Feature","geometry":{"type":"Point","coordinates":[-73.978028,40.671606]},"properties":{"title":"378-730 Smile","marker-color":"#ad6638","marker-size":"small","marker-symbol":"hospital","image":"http:\/\/\/farm3.staticflickr.com\/2553\/3959525918_b3cbaafdb1_q.jpg","url":"http:\/\/\/farm3.staticflickr.com\/2553\/3959525918_b3cbaafdb1.jpg"}},{"type":"Feature","geometry":{"type":"Point","coordinates":[-73.978028,40.671606]},"properties":{"title":"Typewriter","marker-color":"#ad6638","marker-size":"small","marker-symbol":"hospital","image":"http:\/\/\/farm4.staticflickr.com\/3509\/3959520694_7e651c689f_q.jpg","url":"http:\/\/\/farm4.staticflickr.com\/3509\/3959520694_7e651c689f.jpg"}},{"type":"Feature","geometry":{"type":"Point","coordinates":[-73.978028,40.671606]},"properties":{"title":"Typewriter Skeleton","marker-color":"#ad6638","marker-size":"small","marker-symbol":"hospital","image":"http:\/\/\/farm5.staticflickr.com\/4082\/4940962087_0cbfd7b567_q.jpg","url":"http:\/\/\/farm5.staticflickr.com\/4082\/4940962087_0cbfd7b567.jpg"}},{"type":"Feature","geometry":{"type":"Point","coordinates":[-73.962485,40.677772]},"properties":{"title":"All Boro","marker-color":"#ad6638","marker-size":"small","marker-symbol":"hospital","image":"http:\/\/\/farm2.staticflickr.com\/1339\/531094498_7ced3c7916_q.jpg","url":"http:\/\/\/farm2.staticflickr.com\/1339\/531094498_7ced3c7916.jpg"}},{"type":"Feature","geometry":{"type":"Point","coordinates":[-73.972167,40.672833]},"properties":{"title":"Finally found a home for my typewriter","marker-color":"#ad6638","marker-size":"small","marker-symbol":"hospital","image":"http:\/\/\/farm5.staticflickr.com\/4103\/5603665849_a73e44db11_q.jpg","url":"http:\/\/\/farm5.staticflickr.com\/4103\/5603665849_a73e44db11.jpg"}},{"type":"Feature","geometry":{"type":"Point","coordinates":[-73.945274,40.686798]},"properties":{"title":"Rent a Typewriter, 1918","marker-color":"#ad6638","marker-size":"small","marker-symbol":"hospital","image":"http:\/\/\/farm9.staticflickr.com\/8319\/8003153528_23cf20c53b_q.jpg","url":"http:\/\/\/farm9.staticflickr.com\/8319\/8003153528_23cf20c53b.jpg"}},{"type":"Feature","geometry":{"type":"Point","coordinates":[-73.973683,40.791885]},"properties":{"title":"Kristina Contes | right now","marker-color":"#ad6638","marker-size":"small","marker-symbol":"hospital","image":"http:\/\/\/farm4.staticflickr.com\/3044\/2954523995_7a8a27bba2_q.jpg","url":"http:\/\/\/farm4.staticflickr.com\/3044\/2954523995_7a8a27bba2.jpg"}},{"type":"Feature","geometry":{"type":"Point","coordinates":[-73.973683,40.791885]},"properties":{"title":"Kristina Contes | harlem","marker-color":"#ad6638","marker-size":"small","marker-symbol":"hospital","image":"http:\/\/\/farm4.staticflickr.com\/3212\/2955368536_3a2fc10bec_q.jpg","url":"http:\/\/\/farm4.staticflickr.com\/3212\/2955368536_3a2fc10bec.jpg"}},{"type":"Feature","geometry":{"type":"Point","coordinates":[-73.973683,40.791885]},"properties":{"title":"Kristina Contes | chat","marker-color":"#ad6638","marker-size":"small","marker-symbol":"hospital","image":"http:\/\/\/farm4.staticflickr.com\/3004\/2954523049_f63a59a7e8_q.jpg","url":"http:\/\/\/farm4.staticflickr.com\/3004\/2954523049_f63a59a7e8.jpg"}},{"type":"Feature","geometry":{"type":"Point","coordinates":[-73.973683,40.791885]},"properties":{"title":"Kristina Contes | chloe","marker-color":"#ad6638","marker-size":"small","marker-symbol":"hospital","image":"http:\/\/\/farm4.staticflickr.com\/3140\/2955369518_7bfd863f9a_q.jpg","url":"http:\/\/\/farm4.staticflickr.com\/3140\/2955369518_7bfd863f9a.jpg"}},{"type":"Feature","geometry":{"type":"Point","coordinates":[-73.936121,40.697746]},"properties":{"title":"929 Broadway, Bushwick","marker-color":"#ad6638","marker-size":"small","marker-symbol":"hospital","image":"http:\/\/\/farm9.staticflickr.com\/8044\/8362399556_aee2990f3f_q.jpg","url":"http:\/\/\/farm9.staticflickr.com\/8044\/8362399556_aee2990f3f.jpg"}},{"type":"Feature","geometry":{"type":"Point","coordinates":[-73.997998,40.662262]},"properties":{"title":"Typewriter on 23rd","marker-color":"#ad6638","marker-size":"small","marker-symbol":"hospital","image":"http:\/\/\/farm5.staticflickr.com\/4088\/4957952805_705b83d38c_q.jpg","url":"http:\/\/\/farm5.staticflickr.com\/4088\/4957952805_705b83d38c.jpg"}},{"type":"Feature","geometry":{"type":"Point","coordinates":[-73.964381,40.620939]},"properties":{"title":"Trashed Typewriter","marker-color":"#ad6638","marker-size":"small","marker-symbol":"hospital","image":"http:\/\/\/farm3.staticflickr.com\/2250\/2076282075_e37b82a1ac_q.jpg","url":"http:\/\/\/farm3.staticflickr.com\/2250\/2076282075_e37b82a1ac.jpg"}},{"type":"Feature","geometry":{"type":"Point","coordinates":[-73.875467,40.727995]},"properties":{"title":"My grandmothers' #typewriter #JohnSSaturday #vintage #heirloom #antique #keyboard","marker-color":"#ad6638","marker-size":"small","marker-symbol":"hospital","image":"http:\/\/\/farm9.staticflickr.com\/8044\/8375007324_061139d90c_q.jpg","url":"http:\/\/\/farm9.staticflickr.com\/8044\/8375007324_061139d90c.jpg"}},{"type":"Feature","geometry":{"type":"Point","coordinates":[-74.154485,40.739632]},"properties":{"title":"Rose typewriter ribbon and carbon paper","marker-color":"#ad6638","marker-size":"small","marker-symbol":"hospital","image":"http:\/\/\/farm4.staticflickr.com\/3563\/3377519280_dba897c3c2_q.jpg","url":"http:\/\/\/farm4.staticflickr.com\/3563\/3377519280_dba897c3c2.jpg"}},{"type":"Feature","geometry":{"type":"Point","coordinates":[-73.897132,40.862454]},"properties":{"title":"SILVER Sculpture by Christian Marche, The Bronx, New York City","marker-color":"#ad6638","marker-size":"small","marker-symbol":"hospital","image":"http:\/\/\/farm7.staticflickr.com\/6070\/6045863128_4812d253f9_q.jpg","url":"http:\/\/\/farm7.staticflickr.com\/6070\/6045863128_4812d253f9.jpg"}},{"type":"Feature","geometry":{"type":"Point","coordinates":[-74.1715,40.7405]},"properties":{"title":"\"The Typewriter\"","marker-color":"#ad6638","marker-size":"small","marker-symbol":"hospital","image":"http:\/\/\/farm7.staticflickr.com\/6056\/6246851684_634f6942d4_q.jpg","url":"http:\/\/\/farm7.staticflickr.com\/6056\/6246851684_634f6942d4.jpg"}},{"type":"Feature","geometry":{"type":"Point","coordinates":[-74.188582,40.749491]},"properties":{"title":"#typewriter #oldschool #underwood #brick #broken #vintage","marker-color":"#ad6638","marker-size":"small","marker-symbol":"hospital","image":"http:\/\/\/farm6.staticflickr.com\/5456\/9371497284_876f08fe10_q.jpg","url":"http:\/\/\/farm6.staticflickr.com\/5456\/9371497284_876f08fe10.jpg"}}]}